Metadata-Version: 2.1
Name: RNAdist
Version: 0.3.0
Summary: Package for Calculating Expected Distances on the ensemble of RNA structures
Home-page: https://github.com/domonik/RNAdist
Author: domonik
Author-email: dominik.rabsch@gmail.com
License: LICENSE
Requires-Dist: biopython
Requires-Dist: pandas
Requires-Dist: plotly
Requires-Dist: dash>=2.5
Requires-Dist: dash_bootstrap_components
